{
  "generated_at": "2025-10-20T10:46:05.780966+08:00",
  "total_titles_processed": 753,
  "failed_sources": [],
  "trends": [
    {
      "keyword_group": "天数智芯 Iluvatar 壁仞 燧原 摩尔线程 沐曦 瀚博 昆仑芯 寒武纪 华为晟腾 中兴",
      "match_count": 1,
      "titles": [
        {
          "title": "科创板制度优化释放信号！摩尔线程之后，沐曦上会在即",
          "url": "https://www.cls.cn/detail/2173679",
          "source": "财联社热门",
          "ranks": [
            10,
            7
          ],
          "is_new": false,
          "appearance_count": 3,
          "time_info": "[08时59分 ~ 10时46分]"
        }
      ]
    }
  ],
  "report_image_url": "https://github.com/jameskuo3176/TrendRadar/img/news.jpg"
}